Utils/Mongo_conn.py
Utils/MyUtils.py
Utils/Rabbit_conn.py
Utils/Redis_conn.py
Utils/__init__.py
Utils/monitor_rabbit.py
Utils/my_middleware.py
Utils/proxy.py
zhanlanu-0.0.1.dist-info/LICENSE
zhanlanu-0.0.1.dist-info/METADATA
zhanlanu-0.0.1.dist-info/WHEEL
zhanlanu-0.0.1.dist-info/top_level.txt
zhanlanu-0.0.1.dist-info/RECORD
